{"_via_settings":{"ui":{"annotation_editor_height":25,"annotation_editor_fontsize":0.8,"leftsidebar_width":18,"image_grid":{"img_height":80,"rshape_fill":"none","rshape_fill_opacity":0.3,"rshape_stroke":"yellow","rshape_stroke_width":2,"show_region_shape":true,"show_image_policy":"all"},"image":{"region_label":"__via_region_id__","region_color":"Medicine Name","region_label_font":"10px Sans","on_image_annotation_editor_placement":"NEAR_REGION"}},"core":{"buffer_size":18,"filepath":{},"default_filepath":""},"project":{"name":"dr2_1"}},"_via_img_metadata":{"dr2_1.jpg2015254":{"filename":"dr2_1.jpg","size":2015254,"regions":[{"shape_attributes":{"name":"rect","x":493,"y":1109,"width":94,"height":69},"region_attributes":{"Language":"English","Dosage":"\n","Dignostic":"","Symptoms":"","Medicine Name":"","Text":"Tab\n","Personal Information":"","Numeric Data":""}},{"shape_attributes":{"name":"rect","x":668,"y":1083,"width":294,"height":120},"region_attributes":{"Language":"English","Dosage":"","Dignostic":"","Symptoms":"","Medicine Name":"Panadol\n","Text":"","Personal Information":"","Numeric Data":""}},{"shape_attributes":{"name":"rect","x":970,"y":1182,"width":87,"height":60},"region_attributes":{"Language":"English","Dosage":"","Dignostic":"","Symptoms":"","Medicine Name":"","Text":"","Personal Information":"","Numeric Data":"500\n"}},{"shape_attributes":{"name":"rect","x":535,"y":1430,"width":89,"height":69},"region_attributes":{"Language":"English","Dosage":"","Dignostic":"","Symptoms":"","Medicine Name":"","Text":"Cap\n","Personal Information":"","Numeric Data":""}},{"shape_attributes":{"name":"rect","x":734,"y":1428,"width":234,"height":117},"region_attributes":{"Language":"English","Dosage":"","Dignostic":"","Symptoms":"","Medicine Name":"Cefspan\n","Text":"","Personal Information":"","Numeric Data":""}},{"shape_attributes":{"name":"rect","x":1026,"y":1501,"width":93,"height":59},"region_attributes":{"Language":"English","Dosage":"","Dignostic":"","Symptoms":"","Medicine Name":"","Text":"","Personal Information":"","Numeric Data":"400\n"}},{"shape_attributes":{"name":"rect","x":631,"y":1746,"width":85,"height":80},"region_attributes":{"Language":"English","Dosage":"","Dignostic":"","Symptoms":"","Medicine Name":"","Text":"Tab\n","Personal Information":"","Numeric Data":""}},{"shape_attributes":{"name":"rect","x":753,"y":1739,"width":316,"height":108},"region_attributes":{"Language":"English","Dosage":"","Dignostic":"","Symptoms":"","Medicine Name":"Softin Od","Text":"","Personal Information":"","Numeric Data":""}},{"shape_attributes":{"name":"rect","x":647,"y":2050,"width":73,"height":98},"region_attributes":{"Language":"English","Dosage":"\n","Dignostic":"","Symptoms":"","Medicine Name":"","Text":"Tab\n","Personal Information":"","Numeric Data":""}},{"shape_attributes":{"name":"rect","x":815,"y":2062,"width":208,"height":113},"region_attributes":{"Language":"English","Dosage":"","Dignostic":"","Symptoms":"","Medicine Name":"Ventex\n","Text":"","Personal Information":"","Numeric Data":""}},{"shape_attributes":{"name":"rect","x":1038,"y":2124,"width":51,"height":54},"region_attributes":{"Language":"English","Dosage":"","Dignostic":"","Symptoms":"","Medicine Name":"","Text":"","Personal Information":"","Numeric Data":"10\n"}},{"shape_attributes":{"name":"rect","x":696,"y":2371,"width":111,"height":130},"region_attributes":{"Language":"English","Dosage":"","Dignostic":"","Symptoms":"","Medicine Name":"","Text":"Syrup\n","Personal Information":"","Numeric Data":""}},{"shape_attributes":{"name":"rect","x":892,"y":2389,"width":203,"height":127},"region_attributes":{"Language":"English","Dosage":"","Dignostic":"","Symptoms":"","Medicine Name":"Acefyl\n","Text":"","Personal Information":"","Numeric Data":""}},{"shape_attributes":{"name":"rect","x":906,"y":693,"width":294,"height":135},"region_attributes":{"Language":"Urdu","Dosage":"","Dignostic":"","Symptoms":"","Medicine Name":"","Text":"","Personal Information":"یاسمہن بی بی\n","Numeric Data":""}},{"shape_attributes":{"name":"rect","x":1236,"y":951,"width":68,"height":62},"region_attributes":{"Language":"English","Dosage":"","Dignostic":"","Symptoms":"","Medicine Name":"","Text":"","Personal Information":"","Numeric Data":"60\n"}},{"shape_attributes":{"name":"rect","x":1070,"y":929,"width":150,"height":113},"region_attributes":{"Language":"Urdu","Dosage":"","Dignostic":"","Symptoms":"","Medicine Name":"","Text":"سال\n","Personal Information":"","Numeric Data":""}},{"shape_attributes":{"name":"rect","x":842,"y":897,"width":130,"height":96},"region_attributes":{"Language":"Urdu","Dosage":"","Dignostic":"","Symptoms":"","Medicine Name":"","Text":"","Personal Information":"ملتان\n","Numeric Data":""}},{"shape_attributes":{"name":"rect","x":291,"y":1244,"width":80,"height":84},"region_attributes":{"Language":"Urdu","Dosage":"دن\n","Dignostic":"","Symptoms":"","Medicine Name":"","Text":"","Personal Information":"","Numeric Data":""}},{"shape_attributes":{"name":"rect","x":334,"y":1576,"width":96,"height":92},"region_attributes":{"Language":"Urdu","Dosage":"دن\n","Dignostic":"","Symptoms":"","Medicine Name":"","Text":"","Personal Information":"","Numeric Data":""}},{"shape_attributes":{"name":"rect","x":779,"y":1878,"width":154,"height":92},"region_attributes":{"Language":"Urdu","Dosage":"","Dignostic":"","Symptoms":"","Medicine Name":"","Text":"ناٰشتے کے\n","Personal Information":"","Numeric Data":""}},{"shape_attributes":{"name":"rect","x":682,"y":1882,"width":89,"height":61},"region_attributes":{"Language":"Urdu","Dosage":"","Dignostic":"","Symptoms":"","Medicine Name":"","Text":"بعد","Personal Information":"","Numeric Data":""}},{"shape_attributes":{"name":"rect","x":492,"y":1911,"width":59,"height":54},"region_attributes":{"Language":"Urdu","Dosage":"دن","Dignostic":"","Symptoms":"","Medicine Name":"","Text":"","Personal Information":"","Numeric Data":""}},{"shape_attributes":{"name":"rect","x":923,"y":2235,"width":85,"height":75},"region_attributes":{"Language":"Urdu","Dosage":"رات","Dignostic":"","Symptoms":"","Medicine Name":"","Text":"","Personal Information":"","Numeric Data":""}},{"shape_attributes":{"name":"rect","x":869,"y":2195,"width":73,"height":116},"region_attributes":{"Language":"Urdu","Dosage":"","Dignostic":"","Symptoms":"","Medicine Name":"","Text":"کو","Personal Information":"","Numeric Data":""}},{"shape_attributes":{"name":"rect","x":740,"y":2213,"width":122,"height":85},"region_attributes":{"Language":"Urdu","Dosage":"","Dignostic":"","Symptoms":"","Medicine Name":"","Text":"سوتے","Personal Information":"","Numeric Data":""}},{"shape_attributes":{"name":"rect","x":603,"y":2188,"width":133,"height":96},"region_attributes":{"Language":"Urdu","Dosage":"","Dignostic":"","Symptoms":"","Medicine Name":"","Text":"وقت","Personal Information":"","Numeric Data":""}},{"shape_attributes":{"name":"rect","x":381,"y":2212,"width":82,"height":71},"region_attributes":{"Language":"English","Dosage":"دن","Dignostic":"","Symptoms":"","Medicine Name":"","Text":"","Personal Information":"","Numeric Data":""}},{"shape_attributes":{"name":"rect","x":459,"y":2552,"width":82,"height":60},"region_attributes":{"Language":"Urdu","Dosage":"دن","Dignostic":"","Symptoms":"","Medicine Name":"","Text":"","Personal Information":"","Numeric Data":""}},{"shape_attributes":{"name":"rect","x":544,"y":1563,"width":73,"height":118},"region_attributes":{"Language":"Urdu","Dosage":"شام","Dignostic":"","Symptoms":"","Medicine Name":"","Text":"","Personal Information":"","Numeric Data":""}},{"shape_attributes":{"name":"rect","x":622,"y":2497,"width":98,"height":133},"region_attributes":{"Language":"Urdu","Dosage":"شام","Dignostic":"","Symptoms":"","Medicine Name":"","Text":"","Personal Information":"","Numeric Data":""}},{"shape_attributes":{"name":"rect","x":906,"y":1289,"width":29,"height":49},"region_attributes":{"Language":"English","Dosage":"","Dignostic":"","Symptoms":"","Medicine Name":"","Text":"","Personal Information":"","Numeric Data":"2"}},{"shape_attributes":{"name":"rect","x":398,"y":1420,"width":31,"height":37},"region_attributes":{"Language":"English","Dosage":"","Dignostic":"","Symptoms":"","Medicine Name":"","Text":"","Personal Information":"","Numeric Data":"2"}},{"shape_attributes":{"name":"rect","x":941,"y":1619,"width":24,"height":37},"region_attributes":{"Language":"English","Dosage":"","Dignostic":"","Symptoms":"","Medicine Name":"","Text":"","Personal Information":"1\n","Numeric Data":""}},{"shape_attributes":{"name":"rect","x":494,"y":2078,"width":29,"height":61},"region_attributes":{"Language":"English","Dosage":"","Dignostic":"","Symptoms":"","Medicine Name":"","Text":"","Personal Information":"","Numeric Data":"4"}},{"shape_attributes":{"name":"rect","x":486,"y":2227,"width":46,"height":49},"region_attributes":{"Language":"English","Dosage":"","Dignostic":"","Symptoms":"","Medicine Name":"","Text":"","Personal Information":"","Numeric Data":"10"}},{"shape_attributes":{"name":"rect","x":946,"y":1908,"width":37,"height":39},"region_attributes":{"Language":"English","Dosage":"","Dignostic":"","Symptoms":"","Medicine Name":"","Text":"","Personal Information":"","Numeric Data":"1"}},{"shape_attributes":{"name":"rect","x":642,"y":1599,"width":24,"height":32},"region_attributes":{"Language":"English","Dosage":"","Dignostic":"","Symptoms":"","Medicine Name":"","Text":"","Personal Information":"","Numeric Data":"1\n"}}],"file_attributes":{"caption":"","public_domain":"no","image_url":""}}},"_via_attributes":{"region":{"Language":{"type":"dropdown","description":"Language","options":{"Urdu":"Urdu","English":"English"},"default_options":{"unknown":true}},"Dosage":{"type":"text","description":"Suggestions","default_value":"Urdu/english"},"Dignostic":{"type":"text","description":"Name of the object","default_value":"not_defined"},"Symptoms":{"type":"text","description":"Symptoms","default_value":""},"Medicine Name":{"type":"text","description":"Med Name","default_value":"Tab/Syrup/Injection"},"Text":{"type":"text","description":"","default_value":""},"Personal Information":{"type":"text","description":"","default_value":""},"Numeric Data":{"type":"text","description":"","default_value":""}},"file":{"caption":{"type":"text","description":"","default_value":""},"public_domain":{"type":"radio","description":"","options":{"yes":"Yes","no":"No"},"default_options":{"no":true}},"image_url":{"type":"text","description":"","default_value":""}}},"_via_data_format_version":"2.0.10","_via_image_id_list":["dr2_1.jpg2015254"]}